almmf/__init__.py
almmf-1.0.10.dist-info/LICENSE
almmf-1.0.10.dist-info/METADATA
almmf-1.0.10.dist-info/WHEEL
almmf-1.0.10.dist-info/top_level.txt
almmf-1.0.10.dist-info/RECORD
