Metadata-Version: 2.1
Name: almmf
Version: 1.0.10
Summary: Librería optimizada para cálculos paralelos, incluye funciones como suma, máximo, mínimo y promedio, acelerando análisis de grandes datos
Home-page: https://github.com/AnthonyKsos/almmf
Author: antho
Author-email: anthony.mcg24@gmail.com
Classifier: Programming Language :: Python :: 3
Classifier: License :: OSI Approved :: MIT License
Classifier: Operating System :: OS Independent
Requires-Python: >=3.6
License-File: LICENSE
